blob_az/__init__.py
blob_az/blob/__init__.py
blob_az/blob/blob.py
blob_az/container/__init__.py
blob_az/container/container.py
blob_az/env/__init__.py
blob_az/env/keys.py
blob_az/list/__init__.py
blob_az/list/list.py
blob_az/util/__init__.py
blob_az/util/util.py
blob_az-0.2.4.dist-info/METADATA
blob_az-0.2.4.dist-info/WHEEL
blob_az-0.2.4.dist-info/top_level.txt
blob_az-0.2.4.dist-info/RECORD
