Metadata-Version: 2.1
Name: blob-az
Version: 0.2.4
Summary: Async Python SDK for Azure Blob Storage (both block and append blobs)
Author-email: Marcel Claramunt <marcel@moveread.com>
Project-URL: home, https://github.com/moveread/azure-sdks/tree/main/sdks/blob-az
Project-URL: repo, https://github.com/moveread/azure-sdks
Requires-Python: >=3.10
Requires-Dist: azure-storage-blob
Requires-Dist: aiohttp
Requires-Dist: haskellian-asyn
